ol_openedx_rapid_response_reports/__init__.py
ol_openedx_rapid_response_reports/api.py
ol_openedx_rapid_response_reports/app.py
ol_openedx_rapid_response_reports/constants.py
ol_openedx_rapid_response_reports/context_api.py
ol_openedx_rapid_response_reports/urls.py
ol_openedx_rapid_response_reports/utils.py
ol_openedx_rapid_response_reports/docs/__init__.py
ol_openedx_rapid_response_reports/docs/changelog.rst
ol_openedx_rapid_response_reports/docs/conf.py
ol_openedx_rapid_response_reports/docs/readme.rst
ol_openedx_rapid_response_reports/settings/__init__.py
ol_openedx_rapid_response_reports/settings/production.py
ol_openedx_rapid_response_reports/templates/rapid_response.html
ol_openedx_rapid_response_reports-0.4.0.dist-info/METADATA
ol_openedx_rapid_response_reports-0.4.0.dist-info/WHEEL
ol_openedx_rapid_response_reports-0.4.0.dist-info/entry_points.txt
ol_openedx_rapid_response_reports-0.4.0.dist-info/licenses/LICENSE.txt
ol_openedx_rapid_response_reports-0.4.0.dist-info/RECORD
